pyppl_echo.py
pyppl_echo-0.0.6.dist-info/entry_points.txt
pyppl_echo-0.0.6.dist-info/LICENSE
pyppl_echo-0.0.6.dist-info/WHEEL
pyppl_echo-0.0.6.dist-info/METADATA
pyppl_echo-0.0.6.dist-info/RECORD
